clearmacro/__init__.py
clearmacro/client.py
clearmacro/configuration.py
clearmacro/errors.py
clearmacro/events.py
clearmacro/version.py
clearmacro/operations/__init__.py
clearmacro/operations/get_all_markets.py
clearmacro/operations/get_categories_for_universe.py
clearmacro/operations/get_categories_for_universe_id.py
clearmacro/operations/get_market_categories.py
clearmacro/operations/get_markets_for_market_cat.py
clearmacro/operations/get_markets_for_market_cat_id.py
clearmacro/operations/get_markets_for_signal.py
clearmacro/operations/get_markets_for_signal_id.py
clearmacro/operations/get_research_types_for_signal_market_pair.py
clearmacro/operations/get_research_types_for_signal_market_pair_id.py
clearmacro/operations/get_signal_series.py
clearmacro/operations/get_signal_series_id.py
clearmacro/operations/get_signal_universes.py
clearmacro/operations/get_signals_catalogue.py
clearmacro/operations/get_signals_for_market.py
clearmacro/operations/get_signals_for_market_id.py
clearmacro/operations/get_signals_for_universe_cat_pair.py
clearmacro/operations/get_signals_for_universe_cat_pair_id.py
clearmacro/operations/json_to_df.py
clearmacro/operations/login.py
cmqd-1.0.4.dist-info/LICENSE
cmqd-1.0.4.dist-info/METADATA
cmqd-1.0.4.dist-info/WHEEL
cmqd-1.0.4.dist-info/top_level.txt
cmqd-1.0.4.dist-info/RECORD
