Metadata-Version: 2.1
Name: cmqd
Version: 1.0.4
Summary: Python bindings for the ClearMacro API
Home-page: https://github.com/cmqd/cm-api-python-sdk
Author: ClearMacro
Author-email: support@clearmacro.com
License: MIT
Project-URL: Bug Tracker, https://github.com/cmqd/cm-api-python-sdk/issues
Project-URL: Documentation, https://github.com/cmqd/cm-api-python-sdk
Project-URL: Source Code, https://github.com/cmqd/cm-api-python-sdk
Keywords: cmqd clearmacro python api sdk
Platform: UNKNOWN
Requires-Dist: requests[security] (>=2.20) ; python_version < "3.0"
Requires-Dist: pyjwt (>=1.7.1) ; python_version > "3.0"
Requires-Dist: requests (>=2.20) ; python_version >= "3.0"
Requires-Dist: pandas (>=1.1.3) ; python_version >= "3.0"
